f1tel/Drivers.py
f1tel/Layout.py
f1tel/__init__.py
f1tel/__main__.py
f1tel-1.0.0.dist-info/METADATA
f1tel-1.0.0.dist-info/WHEEL
f1tel-1.0.0.dist-info/top_level.txt
f1tel-1.0.0.dist-info/RECORD
